Workbook
Name msg.Eng: [1]RES!$B$59
Name msg.Stat: [1]RES!$B$63
Name Slicer_job_country: #N/A
Name Slicer_﻿job_title_short: #N/A
Name theCell: [1]RES!#REF!

Sheet Dashboard
B2: SALARY INTELLIGENCE DASHBOARD
B5: TOTAL JOBS | G5: AVERAGE SALARY | L5: MEDIAN SALARY
B6: =IFERROR(GETPIVOTDATA("Job Postings",'Monthly Pivot'!$A$3),0) -> 22002 | G6: =IFERROR(GETPIVOTDATA("Average Salary",'Monthly Pivot'!$A$3),"N/A") -> 123287.79 | L6: ='Median Calculation'!E4 -> 115000

Sheet Key Findings
A1: SALARY INTELLIGENCE - KEY FINDINGS
A3: Finding 1: Salary Differences by Job Role
A4: Senior Data Scientists recorded the highest average annual salary at $154,206 across 1,690 postings. The median salary of $155,500 is close to the mean, suggesting limited overall salary skewness.
A6: Finding 2: Remote Salary Premium
A7: Remote positions offered an average annual salary of $131,615, compared with $121,830 for non-remote positions, representing an approximately 8% salary premium. However, this difference is observational and does not establish that remote work directly causes higher compensation.
A9: Finding 3: Overall Salary Distribution
A10: Across 22,002 job postings, the average annual salary was $123,288, compared with a median of $115,000. The higher mean suggests a right-skewed salary distribution, where high-paying positions pull the average upward. Consequently, the median may provide a more representative measure of typical compensation.
A12: Finding 4: Hiring Trends
A13: Job postings declined toward the end of 2023, while average salaries remained relatively stable or increased. One possible explanation is a shift in hiring toward higher-paying, experienced positions. However, further analysis of job seniority and posting volumes would be required to confirm this hypothesis.

Sheet Salary Analysis
A1: Metric | B1: Value
A2: Average Salary | B2: =AVERAGE(jobs[salary_year_avg]) -> 123287.79
A3: Median Salary | B3: =MEDIAN(jobs[salary_year_avg]) -> 115000
A4: Highest Salary | B4: =MAX(jobs[salary_year_avg]) -> 960000
A5: Lowest Salary | B5: =MIN(jobs[salary_year_avg]) -> 15000
A6: # of Jobs | B6: =COUNT(jobs[salary_year_avg]) -> 22002
A10: Job Role | B10: Average Salary | C10: Median Salary | D10: # of Jobs
A11: {=_xlfn.UNIQUE(jobs[﻿job_title_short])} -> Data Scientist | B11: =AVERAGEIF(jobs[﻿job_title_short], A11, jobs[salary_year_avg]) -> 135988.84 | C11: {=MEDIAN(IF(jobs[﻿job_title_short]= A11, jobs[salary_year_avg]))} -> 127500 | D11: =COUNTIF(jobs[﻿job_title_short], A11) -> 5922
A12: Data Engineer | B12: =AVERAGEIF(jobs[﻿job_title_short], A12, jobs[salary_year_avg]) -> 130125.6 | C12: {=MEDIAN(IF(jobs[﻿job_title_short]= A12, jobs[salary_year_avg]))} -> 125000 | D12: =COUNTIF(jobs[﻿job_title_short], A12) -> 4500
A13: Data Analyst | B13: =AVERAGEIF(jobs[﻿job_title_short], A13, jobs[salary_year_avg]) -> 93842.613 | C13: {=MEDIAN(IF(jobs[﻿job_title_short]= A13, jobs[salary_year_avg]))} -> 90000 | D13: =COUNTIF(jobs[﻿job_title_short], A13) -> 5450
A14: Senior Data Engineer | B14: =AVERAGEIF(jobs[﻿job_title_short], A14, jobs[salary_year_avg]) -> 145840.61 | C14: {=MEDIAN(IF(jobs[﻿job_title_short]= A14, jobs[salary_year_avg]))} -> 147500 | D14: =COUNTIF(jobs[﻿job_title_short], A14) -> 1591
A15: Business Analyst | B15: =AVERAGEIF(jobs[﻿job_title_short], A15, jobs[salary_year_avg]) -> 91082.613 | C15: {=MEDIAN(IF(jobs[﻿job_title_short]= A15, jobs[salary_year_avg]))} -> 85000 | D15: =COUNTIF(jobs[﻿job_title_short], A15) -> 610
A16: Software Engineer | B16: =AVERAGEIF(jobs[﻿job_title_short], A16, jobs[salary_year_avg]) -> 113393.76 | C16: {=MEDIAN(IF(jobs[﻿job_title_short]= A16, jobs[salary_year_avg]))} -> 99150 | D16: =COUNTIF(jobs[﻿job_title_short], A16) -> 467
A17: Senior Data Analyst | B17: =AVERAGEIF(jobs[﻿job_title_short], A17, jobs[salary_year_avg]) -> 113911.36 | C17: {=MEDIAN(IF(jobs[﻿job_title_short]= A17, jobs[salary_year_avg]))} -> 111175 | D17: =COUNTIF(jobs[﻿job_title_short], A17) -> 1131
A18: Machine Learning Engineer | B18: =AVERAGEIF(jobs[﻿job_title_short], A18, jobs[salary_year_avg]) -> 126774.32 | C18: {=MEDIAN(IF(jobs[﻿job_title_short]= A18, jobs[salary_year_avg]))} -> 106415 | D18: =COUNTIF(jobs[﻿job_title_short], A18) -> 576
A19: Senior Data Scientist | B19: =AVERAGEIF(jobs[﻿job_title_short], A19, jobs[salary_year_avg]) -> 154206.29 | C19: {=MEDIAN(IF(jobs[﻿job_title_short]= A19, jobs[salary_year_avg]))} -> 155500 | D19: =COUNTIF(jobs[﻿job_title_short], A19) -> 1690
A20: Cloud Engineer | B20: =AVERAGEIF(jobs[﻿job_title_short], A20, jobs[salary_year_avg]) -> 111268.45 | C20: {=MEDIAN(IF(jobs[﻿job_title_short]= A20, jobs[salary_year_avg]))} -> 90000 | D20: =COUNTIF(jobs[﻿job_title_short], A20) -> 65
A23: Work Type | B23: Average Salary | C23: Median Salary | D23: # of Jobs | E23: % of Total Jobs | F23: Avg Salary Premium
A24: Remote | B24: {=AVERAGE(_xlfn._xlws.FILTER(jobs[salary_year_avg],jobs[job_work_from_home]="True"))} -> 131614.59 | C24: {=MEDIAN(_xlfn._xlws.FILTER(jobs[salary_year_avg], jobs[job_work_from_home] = "TRUE"))} -> 128914.81 | D24: {=COUNT(_xlfn._xlws.FILTER(jobs[salary_year_avg], jobs[job_work_from_home] = "True"))} -> 3278 | E24: =(D24)/(D24+D25) -> 0.14898646 | F24: =(B24-B25)/(B25) -> 0.080313316
A25: Non-Remote | B25: {=AVERAGE(_xlfn._xlws.FILTER(jobs[salary_year_avg],jobs[job_work_from_home]="False"))} -> 121830.02 | C25: {=MEDIAN(_xlfn._xlws.FILTER(jobs[salary_year_avg], jobs[job_work_from_home] = "False"))} -> 115000 | D25: {=COUNT(_xlfn._xlws.FILTER(jobs[salary_year_avg], jobs[job_work_from_home] = "False"))} -> 18724 | E25: =(D25)/(D24+D25) -> 0.85101354 | F25: -
A27: Country | B27: Average Salary | C27: Median Salary | D27: # of Jobs | E27: Sample Size Status
A28: {=_xlfn.UNIQUE(jobs[job_country])} -> Costa Rica | B28: {=AVERAGE(_xlfn._xlws.FILTER(jobs[salary_year_avg], jobs[job_country] = A28))} -> 110484.87 | C28: {=MEDIAN(_xlfn._xlws.FILTER(jobs[salary_year_avg], jobs[job_country] = A28))} -> 107025 | D28: {=COUNT(_xlfn._xlws.FILTER(jobs[salary_year_avg], jobs[job_country] = A28))} -> 42 | E28: =IF(D28>=100, "Include", "Exclude") -> Exclude
A29: Sudan | B29: {=AVERAGE(_xlfn._xlws.FILTER(jobs[salary_year_avg], jobs[job_country] = A29))} -> 134051.58 | C29: {=MEDIAN(_xlfn._xlws.FILTER(jobs[salary_year_avg], jobs[job_country] = A29))} -> 129500 | D29: {=COUNT(_xlfn._xlws.FILTER(jobs[salary_year_avg], jobs[job_country] = A29))} -> 1623 | E29: =IF(D29>=100, "Include", "Exclude") -> Include
A30: United States | B30: {=AVERAGE(_xlfn._xlws.FILTER(jobs[salary_year_avg], jobs[job_country] = A30))} -> 126136.78 | C30: {=MEDIAN(_xlfn._xlws.FILTER(jobs[salary_year_avg], jobs[job_country] = A30))} -> 119200 | D30: {=COUNT(_xlfn._xlws.FILTER(jobs[salary_year_avg], jobs[job_country] = A30))} -> 15765 | E30: =IF(D30>=100, "Include", "Exclude") -> Include
A31: Belgium | B31: {=AVERAGE(_xlfn._xlws.FILTER(jobs[salary_year_avg], jobs[job_country] = A31))} -> 96550.623 | C31: {=MEDIAN(_xlfn._xlws.FILTER(jobs[salary_year_avg], jobs[job_country] = A31))} -> 89100 | D31: {=COUNT(_xlfn._xlws.FILTER(jobs[salary_year_avg], jobs[job_country] = A31))} -> 57 | E31: =IF(D31>=100, "Include", "Exclude") -> Exclude
A32: Honduras | B32: {=AVERAGE(_xlfn._xlws.FILTER(jobs[salary_year_avg], jobs[job_country] = A32))} -> 63000 | C32: {=MEDIAN(_xlfn._xlws.FILTER(jobs[salary_year_avg], jobs[job_country] = A32))} -> 63000 | D32: {=COUNT(_xlfn._xlws.FILTER(jobs[salary_year_avg], jobs[job_country] = A32))} -> 1 | E32: =IF(D32>=100, "Include", "Exclude") -> Exclude
A33: Denmark | B33: {=AVERAGE(_xlfn._xlws.FILTER(jobs[salary_year_avg], jobs[job_country] = A33))} -> 111008.47 | C33: {=MEDIAN(_xlfn._xlws.FILTER(jobs[salary_year_avg], jobs[job_country] = A33))} -> 105475 | D33: {=COUNT(_xlfn._xlws.FILTER(jobs[salary_year_avg], jobs[job_country] = A33))} -> 18 | E33: =IF(D33>=100, "Include", "Exclude") -> Exclude
A34: United Kingdom | B34: {=AVERAGE(_xlfn._xlws.FILTER(jobs[salary_year_avg], jobs[job_country] = A34))} -> 109951.15 | C34: {=MEDIAN(_xlfn._xlws.FILTER(jobs[salary_year_avg], jobs[job_country] = A34))} -> 104668 | D34: {=COUNT(_xlfn._xlws.FILTER(jobs[salary_year_avg], jobs[job_country] = A34))} -> 287 | E34: =IF(D34>=100, "Include", "Exclude") -> Include
A35: India | B35: {=AVERAGE(_xlfn._xlws.FILTER(jobs[salary_year_avg], jobs[job_country] = A35))} -> 113602.18 | C35: {=MEDIAN(_xlfn._xlws.FILTER(jobs[salary_year_avg], jobs[job_country] = A35))} -> 111175 | D35: {=COUNT(_xlfn._xlws.FILTER(jobs[salary_year_avg], jobs[job_country] = A35))} -> 582 | E35: =IF(D35>=100, "Include", "Exclude") -> Include
A36: Israel | B36: {=AVERAGE(_xlfn._xlws.FILTER(jobs[salary_year_avg], jobs[job_country] = A36))} -> 111304.06 | C36: {=MEDIAN(_xlfn._xlws.FILTER(jobs[salary_year_avg], jobs[job_country] = A36))} -> 111175 | D36: {=COUNT(_xlfn._xlws.FILTER(jobs[salary_year_avg], jobs[job_country] = A36))} -> 103 | E36: =IF(D36>=100, "Include", "Exclude") -> Include
A37: Germany | B37: {=AVERAGE(_xlfn._xlws.FILTER(jobs[salary_year_avg], jobs[job_country] = A37))} -> 115800.56 | C37: {=MEDIAN(_xlfn._xlws.FILTER(jobs[salary_year_avg], jobs[job_country] = A37))} -> 111175 | D37: {=COUNT(_xlfn._xlws.FILTER(jobs[salary_year_avg], jobs[job_country] = A37))} -> 257 | E37: =IF(D37>=100, "Include", "Exclude") -> Include
A38: Hungary | B38: {=AVERAGE(_xlfn._xlws.FILTER(jobs[salary_year_avg], jobs[job_country] = A38))} -> 104035.14 | C38: {=MEDIAN(_xlfn._xlws.FILTER(jobs[salary_year_avg], jobs[job_country] = A38))} -> 92936.5 | D38: {=COUNT(_xlfn._xlws.FILTER(jobs[salary_year_avg], jobs[job_country] = A38))} -> 62 | E38: =IF(D38>=100, "Include", "Exclude") -> Exclude
A39: Poland | B39: {=AVERAGE(_xlfn._xlws.FILTER(jobs[salary_year_avg], jobs[job_country] = A39))} -> 106946.17 | C39: {=MEDIAN(_xlfn._xlws.FILTER(jobs[salary_year_avg], jobs[job_country] = A39))} -> 98391.5 | D39: {=COUNT(_xlfn._xlws.FILTER(jobs[salary_year_avg], jobs[job_country] = A39))} -> 200 | E39: =IF(D39>=100, "Include", "Exclude") -> Include
A40: Portugal | B40: {=AVERAGE(_xlfn._xlws.FILTER(jobs[salary_year_avg], jobs[job_country] = A40))} -> 116437.67 | C40: {=MEDIAN(_xlfn._xlws.FILTER(jobs[salary_year_avg], jobs[job_country] = A40))} -> 111175 | D40: {=COUNT(_xlfn._xlws.FILTER(jobs[salary_year_avg], jobs[job_country] = A40))} -> 131 | E40: =IF(D40>=100, "Include", "Exclude") -> Include
... A135: Bosnia and Herzegovina | B135: {=AVERAGE(_xlfn._xlws.FILTER(jobs[salary_year_avg], jobs[job_country] = A135))} -> 89100 | C135: {=MEDIAN(_xlfn._xlws.FILTER(jobs[salary_year_avg], jobs[job_country] = A135))} -> 89100 | D135: {=COUNT(_xlfn._xlws.FILTER(jobs[salary_year_avg], jobs[job_country] = A135))} -> 1 | E135: =IF(D135>=100, "Include", "Exclude") -> Exclude
A140: Country | B140: Average Salary | C140: Median Salary | D140: # of Jobs | E140: Sample Size Status
A141: Sudan | B141: 134051.58 | C141: 129500 | D141: 1623 | E141: Include
A142: United States | B142: 126136.78 | C142: 119200 | D142: 15765 | E142: Include
A143: Canada | B143: 123121.53 | C143: 115000 | D143: 463 | E143: Include
A144: Portugal | B144: 116437.67 | C144: 111175 | D144: 131 | E144: Include
A145: Germany | B145: 115800.56 | C145: 111175 | D145: 257 | E145: Include
A146: Mexico | B146: 114950.24 | C146: 109500 | D146: 111 | E146: Include
A147: India | B147: 113602.18 | C147: 111175 | D147: 582 | E147: Include
A148: Israel | B148: 111304.06 | C148: 111175 | D148: 103 | E148: Include
A149: United Kingdom | B149: 109951.15 | C149: 104668 | D149: 287 | E149: Include
A150: Spain | B150: 107357.19 | C150: 98391.5 | D150: 144 | E150: Include
A151: Poland | B151: 106946.17 | C151: 98391.5 | D151: 200 | E151: Include
A152: France | B152: 104511.66 | C152: 97444 | D152: 237 | E152: Include

Sheet Time Analysis
A1: Earliest Posting Date | B1: =MIN('Salary Data'!G:G) -> 44927.002
A2: Lastest Posting Date | B2: =MAX('Salary Data'!G:G) -> 45291.986
A6: Month | B6: # of Jobs | C6: Average Salary | D6: Median Salary
A7: =MIN('Salary Data'!G:G) -> 44927.002 | B7: {=COUNT(_xlfn._xlws.FILTER(jobs[job_posted_date], (jobs[job_posted_date]>=A7) *(jobs[job_posted_date]<A8) ))} -> 2296 | C7: {=AVERAGE(_xlfn._xlws.FILTER(jobs[salary_year_avg], (jobs[job_posted_date]>=A7) *(jobs[job_posted_date]<A8) ))} -> 123007.42 | D7: {=MEDIAN(_xlfn._xlws.FILTER(jobs[salary_year_avg], (jobs[job_posted_date]>=A7) *(jobs[job_posted_date]<A8) ))} -> 115000
A8: =EDATE(B1, 1) -> 44958 | B8: {=COUNT(_xlfn._xlws.FILTER(jobs[job_posted_date], (jobs[job_posted_date]>=A8) *(jobs[job_posted_date]<A9) ))} -> 2010 | C8: {=AVERAGE(_xlfn._xlws.FILTER(jobs[salary_year_avg], (jobs[job_posted_date]>=A8) *(jobs[job_posted_date]<A9) ))} -> 122913.93 | D8: {=MEDIAN(_xlfn._xlws.FILTER(jobs[salary_year_avg], (jobs[job_posted_date]>=A8) *(jobs[job_posted_date]<A9) ))} -> 115000
A9: =EDATE(A8, 1) -> 44986 | B9: {=COUNT(_xlfn._xlws.FILTER(jobs[job_posted_date], (jobs[job_posted_date]>=A9) *(jobs[job_posted_date]<A10) ))} -> 2204 | C9: {=AVERAGE(_xlfn._xlws.FILTER(jobs[salary_year_avg], (jobs[job_posted_date]>=A9) *(jobs[job_posted_date]<A10) ))} -> 122947.81 | D9: {=MEDIAN(_xlfn._xlws.FILTER(jobs[salary_year_avg], (jobs[job_posted_date]>=A9) *(jobs[job_posted_date]<A10) ))} -> 117050
A10: =EDATE(A9, 1) -> 45017 | B10: {=COUNT(_xlfn._xlws.FILTER(jobs[job_posted_date], (jobs[job_posted_date]>=A10) *(jobs[job_posted_date]<A11) ))} -> 1876 | C10: {=AVERAGE(_xlfn._xlws.FILTER(jobs[salary_year_avg], (jobs[job_posted_date]>=A10) *(jobs[job_posted_date]<A11) ))} -> 121856.55 | D10: {=MEDIAN(_xlfn._xlws.FILTER(jobs[salary_year_avg], (jobs[job_posted_date]>=A10) *(jobs[job_posted_date]<A11) ))} -> 115000
A11: =EDATE(A10, 1) -> 45047 | B11: {=COUNT(_xlfn._xlws.FILTER(jobs[job_posted_date], (jobs[job_posted_date]>=A11) *(jobs[job_posted_date]<A12) ))} -> 1911 | C11: {=AVERAGE(_xlfn._xlws.FILTER(jobs[salary_year_avg], (jobs[job_posted_date]>=A11) *(jobs[job_posted_date]<A12) ))} -> 123656.75 | D11: {=MEDIAN(_xlfn._xlws.FILTER(jobs[salary_year_avg], (jobs[job_posted_date]>=A11) *(jobs[job_posted_date]<A12) ))} -> 115000
A12: =EDATE(A11, 1) -> 45078 | B12: {=COUNT(_xlfn._xlws.FILTER(jobs[job_posted_date], (jobs[job_posted_date]>=A12) *(jobs[job_posted_date]<A13) ))} -> 2331 | C12: {=AVERAGE(_xlfn._xlws.FILTER(jobs[salary_year_avg], (jobs[job_posted_date]>=A12) *(jobs[job_posted_date]<A13) ))} -> 124321.14 | D12: {=MEDIAN(_xlfn._xlws.FILTER(jobs[salary_year_avg], (jobs[job_posted_date]>=A12) *(jobs[job_posted_date]<A13) ))} -> 115000
A13: =EDATE(A12, 1) -> 45108 | B13: {=COUNT(_xlfn._xlws.FILTER(jobs[job_posted_date], (jobs[job_posted_date]>=A13) *(jobs[job_posted_date]<A14) ))} -> 2219 | C13: {=AVERAGE(_xlfn._xlws.FILTER(jobs[salary_year_avg], (jobs[job_posted_date]>=A13) *(jobs[job_posted_date]<A14) ))} -> 123470.57 | D13: {=MEDIAN(_xlfn._xlws.FILTER(jobs[salary_year_avg], (jobs[job_posted_date]>=A13) *(jobs[job_posted_date]<A14) ))} -> 115000
A14: =EDATE(A13, 1) -> 45139 | B14: {=COUNT(_xlfn._xlws.FILTER(jobs[job_posted_date], (jobs[job_posted_date]>=A14) *(jobs[job_posted_date]<A15) ))} -> 2095 | C14: {=AVERAGE(_xlfn._xlws.FILTER(jobs[salary_year_avg], (jobs[job_posted_date]>=A14) *(jobs[job_posted_date]<A15) ))} -> 125819.43 | D14: {=MEDIAN(_xlfn._xlws.FILTER(jobs[salary_year_avg], (jobs[job_posted_date]>=A14) *(jobs[job_posted_date]<A15) ))} -> 115000
A15: =EDATE(A14, 1) -> 45170 | B15: {=COUNT(_xlfn._xlws.FILTER(jobs[job_posted_date], (jobs[job_posted_date]>=A15) *(jobs[job_posted_date]<A16) ))} -> 1245 | C15: {=AVERAGE(_xlfn._xlws.FILTER(jobs[salary_year_avg], (jobs[job_posted_date]>=A15) *(jobs[job_posted_date]<A16) ))} -> 125251.28 | D15: {=MEDIAN(_xlfn._xlws.FILTER(jobs[salary_year_avg], (jobs[job_posted_date]>=A15) *(jobs[job_posted_date]<A16) ))} -> 118000
A16: =EDATE(A15, 1) -> 45200 | B16: {=COUNT(_xlfn._xlws.FILTER(jobs[job_posted_date], (jobs[job_posted_date]>=A16) *(jobs[job_posted_date]<A17) ))} -> 1310 | C16: {=AVERAGE(_xlfn._xlws.FILTER(jobs[salary_year_avg], (jobs[job_posted_date]>=A16) *(jobs[job_posted_date]<A17) ))} -> 124606.65 | D16: {=MEDIAN(_xlfn._xlws.FILTER(jobs[salary_year_avg], (jobs[job_posted_date]>=A16) *(jobs[job_posted_date]<A17) ))} -> 117803
A17: =EDATE(A16, 1) -> 45231 | B17: {=COUNT(_xlfn._xlws.FILTER(jobs[job_posted_date], (jobs[job_posted_date]>=A17) *(jobs[job_posted_date]<A18) ))} -> 1124 | C17: {=AVERAGE(_xlfn._xlws.FILTER(jobs[salary_year_avg], (jobs[job_posted_date]>=A17) *(jobs[job_posted_date]<A18) ))} -> 119817.18 | D17: {=MEDIAN(_xlfn._xlws.FILTER(jobs[salary_year_avg], (jobs[job_posted_date]>=A17) *(jobs[job_posted_date]<A18) ))} -> 112392
A18: =EDATE(A17, 1) -> 45261 | B18: {=COUNT(_xlfn._xlws.FILTER(jobs[job_posted_date], (jobs[job_posted_date]>=A18) *(jobs[job_posted_date]<A19) ))} -> 1381 | C18: {=AVERAGE(_xlfn._xlws.FILTER(jobs[salary_year_avg], (jobs[job_posted_date]>=A18) *(jobs[job_posted_date]<A19) ))} -> 120199.42 | D18: {=MEDIAN(_xlfn._xlws.FILTER(jobs[salary_year_avg], (jobs[job_posted_date]>=A18) *(jobs[job_posted_date]<A19) ))} -> 112500
A19: =EDATE(A18, 1) -> 45292

Sheet Data Quality
A1: =COUNTBLANK(jobs[﻿job_title_short]) -> 0 | B1: =COUNTBLANK(jobs[job_title]) -> 0 | C1: =COUNTBLANK(jobs[job_location]) -> 280 | D1: =COUNTBLANK(jobs[job_schedule_type]) -> 16 | E1: =COUNTBLANK(jobs[job_work_from_home]) -> 0 | F1: =COUNTBLANK(jobs[job_country]) -> 0 | G1: =COUNTBLANK(jobs[job_posted_date]) -> 0 | H1: =COUNTBLANK(jobs[salary_year_avg]) -> 0 | I1: =COUNTBLANK(jobs[company_name]) -> 0 | J1: =COUNTBLANK(jobs[job_skills]) -> 1833 | K1: =J1/22002 -> 0.083310608

Sheet Median Calculation
A3: Row Labels | B3: Count of salary_year_avg | C3: Cumulative Count | D3: Filtered Median Salary
A4: 15000 | B4: 1 | C4: =SUM($B$4:B4) -> 1 | D4: =IFERROR(AVERAGE(_xlfn.XLOOKUP(INT((SUM(B4:B28)+1)/2),C4:C28,A4:A28,,1),_xlfn.XLOOKUP(INT((SUM(B4:B28)+2)/2),C4:C28,A4:A28,,1)),"N/A") -> 32500 | E4: {=IFERROR(_xlfn.LET(_xlpm.s,_xlfn._xlws.FILTER(A4:A22005,ISNUMBER(A4:A22005)),_xlpm.c,_xlfn._xlws.FILTER(B4:B22005,ISNUMBER(A4:A22005)),_xlpm.n,SUM(_xlpm.c),_xlpm.running,_xlfn.SCAN(0,_xlpm.c,_xlfn.LAMBDA(_xlpm.a,_xlpm.b,_xlpm.a+_xlpm.b)),AVERAGE(_xlfn.XLOOKUP(INT((_xlpm.n+1)/2),_xlpm.running,_xlpm.s,,1),_xlfn.XLOOKUP(INT((_xlpm.n+2)/2),_xlpm.running,_xlpm.s,,1))),"N/A")} -> 115000
A5: 16500 | B5: 1 | C5: =SUM($B$4:B5) -> 2
A6: 20000 | B6: 1 | C6: =SUM($B$4:B6) -> 3
A7: 23496 | B7: 1 | C7: =SUM($B$4:B7) -> 4
A8: 24000 | B8: 1 | C8: =SUM($B$4:B8) -> 5
A9: 25000 | B9: 3 | C9: =SUM($B$4:B9) -> 8
A10: 25920 | B10: 1 | C10: =SUM($B$4:B10) -> 9
A11: 26444 | B11: 1 | C11: =SUM($B$4:B11) -> 10
A12: 27000 | B12: 1 | C12: =SUM($B$4:B12) -> 11
A13: 28000 | B13: 1 | C13: =SUM($B$4:B13) -> 12
A14: 29900 | B14: 1 | C14: =SUM($B$4:B14) -> 13
A15: 30000 | B15: 11 | C15: =SUM($B$4:B15) -> 24
A16: 30594 | B16: 1 | C16: =SUM($B$4:B16) -> 25
... A28: 35360 | B28: 2 | C28: =SUM($B$4:B28) -> 61
A29: 36000 | B29: 8
A30: 37107.199 | B30: 1
A31: 37250 | B31: 1
A32: 37499.5 | B32: 1
A33: 37500 | B33: 6
A34: 37860 | B34: 2
A35: 38000 | B35: 2
A36: 38750 | B36: 2
A37: 39000 | B37: 2
A38: 39250 | B38: 1
A39: 39500 | B39: 1
A40: 39531 | B40: 1
... A2705: 960000 | B2705: 1
A2706: Grand Total | B2706: 22002

Sheet Salary Data
A1: ﻿job_title_short | B1: job_title | C1: job_location | D1: job_schedule_type | E1: job_work_from_home | F1: job_country | G1: job_posted_date | H1: salary_year_avg | I1: company_name | J1: job_skills
A2: Data Scientist | B2: CRM Data Specialist | C2: San José Province, San José, Costa Rica | D2: Full-time | E2: False | F2: Costa Rica | G2: 45139.568 | H2: 109500 | I2: Netskope | J2: ['gdpr', 'excel']
A3: Data Engineer | B3: Data Engineer | C3: Arlington, VA | D3: Full-time | E3: False | F3: Sudan | G3: 45103.599 | H3: 140000 | I3: Intelletec | J3: ['mongodb', 'mongodb', 'python', 'r', 'sql', 'mysql', 'mariadb', 'oracle', 'spark', 'tableau', 'kubernetes']
A4: Data Engineer | B4: Remote - Data Engineer - Permanent - W2 | C4: Anywhere | D4: Full-time | E4: True | F4: United States | G4: 44978.562 | H4: 120000 | I4: Apex Systems | J4: ['sql', 'python']
A5: Data Scientist | B5: Data Scientist, Risk Data Mining - USDS | C5: Mountain View, CA | D5: Full-time | E5: False | F5: United States | G5: 45138.543 | H5: 228222 | I5: TikTok | J5: ['sql', 'r', 'python', 'express']
A6: Data Analyst | B6: Senior Supply Chain Analytics Analyst | C6: Anywhere | D6: Full-time | E6: True | F6: United States | G6: 45211.543 | H6: 89000 | I6: Get It Recruit - Transportation | J6: ['python', 'r', 'alteryx', 'tableau']
A7: Data Scientist | B7: Data Scientist | C7: Anywhere | D7: Full-time | E7: True | F7: United States | G7: 45203.545 | H7: 114000 | I7: 4 Corner Resources | J7: ['r', 'python', 'sql', 't-sql', 'hadoop', 'spark', 'tableau']
A8: Data Engineer | B8: Data Engineer Graduate (Real Time Communication) - 2024 Start (BS/ MS) | C8: Seattle, WA | D8: Full-time | E8: False | F8: United States | G8: 45220.546 | H8: 129500 | I8: ByteDance | J8: ['golang', 'scala', 'python', 'java', 'hadoop', 'spark']
A9: Data Analyst | B9: Data Analyst III | C9: Dos Palos, CA | D9: Full-time | E9: False | F9: United States | G9: 44984.542 | H9: 90250 | I9: California Health & Wellness | J9: ['excel', 'powerpoint']
A10: Data Scientist | B10: NATOIS-0008 Data Scientist (NS) - TUE 13 Jun | C10: Brussels, Belgium | D10: Full-time | E10: False | F10: Belgium | G10: 45082.581 | H10: 157500 | I10: EMW, Inc. | J10: ['c', 'r', 'sql', 'python', 'aws', 'azure', 'hadoop', 'tableau']
A11: Data Scientist | B11: Senior Bioinformatics Research Scientist- Data Scientist | C11: Brighton, TN | D11: Full-time | E11: False | F11: United States | G11: 45250.57 | H11: 103128 | I11: St. Jude Children's Research Hospital | J11: ['r', 'electron']
A12: Data Engineer | B12: Data Engineer | C12: Austin, TX | D12: Full-time | E12: False | F12: United States | G12: 45202.545 | H12: 185000 | I12: hackajob | J12: ['nosql', 'sql']
A13: Data Engineer | B13: Global Market Leading Energy Firm - Staff Data Engineer | C13: United States | D13: Full-time | E13: False | F13: United States | G13: 45191.547 | H13: 195000 | I13: Xcede
A14: Data Engineer | B14: Snaplogic Data Engineer | C14: Durham, NC | D14: Full-time | E14: False | F14: United States | G14: 45154.56 | H14: 97500 | I14: KTek Resourcing | J14: ['sql', 'python']
A15: Data Engineer | B15: Data Engineer | C15: New Ulm, MN | D15: Full-time | E15: False | F15: United States | G15: 45158.564 | H15: 89000 | I15: Ledgent Technology | J15: ['sql', 'python', 'power bi']
A16: Data Analyst | B16: IT Business Lead Data Analyst - VP - Hybrid | C16: Atlantic Beach, FL | D16: Full-time | E16: False | F16: United States | G16: 44936.583 | H16: 133285 | I16: Citi | J16: ['sql', 'word', 'excel', 'visio', 'powerpoint', 'sharepoint']
A17: Data Scientist | B17: Data Defense Developer - USDS | C17: Mountain View, CA | D17: Full-time | E17: False | F17: United States | G17: 45262.556 | H17: 157500 | I17: TikTok | J17: ['go', 'python', 'java', 'mongo', 'redis', 'aws', 'pandas', 'numpy', 'kafka', 'express', 'github', 'bitbucket']
A18: Senior Data Engineer | B18: Senior Software Engineer (Data) | C18: San Francisco, CA | D18: Full-time | E18: False | F18: United States | G18: 45097.547 | H18: 168500 | I18: hackajob | J18: ['scala', 'gcp', 'azure', 'spark', 'kafka', 'hadoop', 'terraform', 'git', 'jenkins', 'gitlab']
A19: Business Analyst | B19: Power BI Analyst | C19: San Pedro Sula, Honduras | D19: Full-time | E19: False | F19: Honduras | G19: 45131.587 | H19: 63000 | I19: Charger Logistics Inc | J19: ['power bi']
A20: Data Engineer | B20: ERP Data Engineer | C20: Lansing, MI | D20: Full-time | E20: False | F20: Sudan | G20: 44930.582 | H20: 80000 | I20: Venteon | J20: ['sql', 'sap']
A21: Data Engineer | B21: Data Engineer ETL lnformatica API SQL Engineer (DIRECT HIRE) | C21: Anywhere | D21: Full-time | E21: True | F21: United States | G21: 45127.547 | H21: 110000 | I21: Robert Half | J21: ['sql', 'java', 'python', 'azure', 'aws', 'snowflake']
A22: Senior Data Engineer | B22: Senior Python Data Engineer | C22: Wilmington, DE | D22: Full-time | E22: False | F22: Sudan | G22: 45185.551 | H22: 160000 | I22: Crackajack Solutions | J22: ['python', 'sql', 'java', 'aws', 'databricks', 'redshift', 'spark', 'pyspark', 'hadoop']
A23: Business Analyst | B23: Lead BI Analyst | C23: Irvine, CA | D23: Full-time | E23: False | F23: United States | G23: 45149.543 | H23: 125000 | I23: KORE1 | J23: ['sql', 'python', 'tableau']
A24: Data Engineer | B24: Lead Data Engineer (DataStage) (Need only locals Cincinnati, OH) | C24: Cincinnati, OH | D24: Contractor | E24: False | F24: Sudan | G24: 45191.569 | H24: 70000 | I24: Strategic Systems Inc
A25: Senior Data Engineer | B25: Senior Data Engineer | Series D Video Analytics Start-Up (200-250 TC) | C25: Culver City, CA | D25: Full-time | E25: False | F25: United States | G25: 45208.589 | H25: 165000 | I25: Coda Search│Staffing | J25: ['python', 'scala', 'sql', 'aws', 'redshift', 'spark', 'pandas']
A26: Software Engineer | B26: Tech Lead Software Engineer, TikTok Data Access | C26: San Jose, CA | D26: Full-time | E26: False | F26: United States | G26: 45291.544 | H26: 317000 | I26: TikTok | J26: ['java', 'go', 'c++', 'python', 'mongodb', 'mongodb', 'mysql', 'redis']
A27: Data Engineer | B27: Data Engineer, Azure | C27: United States | D27: Full-time and Contractor | E27: False | F27: United States | G27: 45210.547 | H27: 100000 | I27: Technical Source | J27: ['sql', 'python', 'azure', 'databricks']
A28: Data Engineer | B28: Azure Data Engineer | C28: Scottsdale, AZ | D28: Full-time | E28: False | F28: United States | G28: 45061.558 | H28: 111228.16 | I28: TEKletics | J28: ['sql', 'python', 'azure']
A29: Senior Data Engineer | B29: Senior Data Engineer (Hybrid) | C29: Washington, DC | D29: Full-time | E29: False | F29: United States | G29: 45048.548 | H29: 173500 | I29: Capital One | J29: ['java', 'scala', 'python', 'nosql', 'sql', 'shell', 'mysql', 'dynamodb', 'redshift', 'snowflake', 'aws', 'azure', 'hadoop', 'kafka', 'spark']
A30: Senior Data Engineer | B30: Senior Data Engineer | C30: Oakland, CA | D30: Full-time | E30: False | F30: Sudan | G30: 45113.571 | H30: 160000 | I30: X4 Life Sciences | J30: ['python', 'sql', 'postgresql', 'sql server', 'aws', 'snowflake']
A31: Data Engineer | B31: Data Engineer, Big Data Privacy and Security | C31: San Jose, CA | D31: Full-time | E31: False | F31: Sudan | G31: 45095.569 | H31: 171000 | I31: TikTok | J31: ['spark', 'kafka']
A32: Data Engineer | B32: Principal Data Engineer | C32: Anywhere | D32: Full-time | E32: True | F32: United States | G32: 45063.557 | H32: 180000 | I32: CyberCoders | J32: ['sql', 'python', 'aws', 'snowflake', 'spark', 'hadoop', 'tableau', 'microstrategy']
A33: Data Engineer | B33: Azure Data Engineer | C33: United States | D33: Full-time | E33: False | F33: United States | G33: 44985.551 | H33: 157500 | I33: Jobot | J33: ['t-sql', 'c#', 'python', 'sql', 'azure', 'github']
A34: Data Engineer | B34: AWS Data Engineer | C34: Anywhere | D34: Full-time | E34: True | F34: United States | G34: 45147.546 | H34: 135000 | I34: Effectual Inc. | J34: ['python', 'sql', 'java', 'scala', 'nosql', 'aws', 'azure', 'redshift', 'bigquery', 'spark', 'hadoop', 'airflow']
A35: Senior Data Analyst | B35: Senior Data Analyst | C35: Los Angeles, CA | D35: Full-time | E35: False | F35: United States | G35: 44960.543 | H35: 85000 | I35: Jobot | J35: ['sas', 'sas']
A36: Data Analyst | B36: DATA ANALYST (ONSITE) | C36: Springfield, MA | D36: Full-time | E36: False | F36: United States | G36: 45251.542 | H36: 62623 | I36: Springfield Public Schools | J36: ['sql', 'excel', 'tableau']
... A39: Senior Data Engineer | B39: Senior Data Engineer | C39: Southfield, MI | D39: Full-time | E39: False | F39: United States | G39: 45147.545 | H39: 90000 | I39: Sun Communities | J39: ['sql', 'python', 'c#', 'java', 'javascript', 'azure', 'databricks']
A40: Machine Learning Engineer | B40: Head of AML Operations (m/f/d) | C40: Ballerup, Denmark | D40: Full-time | E40: False | F40: Denmark | G40: 45091.559 | H40: 105300 | I40: Nets
A41: Data Engineer | B41: Data Engineer | C41: Dallas, TX | D41: Full-time | E41: False | F41: United States | G41: 45026.548 | H41: 137500 | I41: WEX | J41: ['go', 'python', 'pyspark', 'spark']
A42: Data Scientist | B42: Data Scientist, Customer AI Engineering | C42: London, UK | D42: Full-time | E42: False | F42: United Kingdom | G42: 45097.551 | H42: 157500 | I42: Tractable | J42: ['python', 'numpy', 'pandas', 'scikit-learn']
A43: Senior Data Engineer | B43: Senior Data Engineer | C43: San Mateo, CA | D43: Full-time | E43: False | F43: Sudan | G43: 45063.591 | H43: 155000 | I43: Intelletec | J43: ['python', 'aws']
A44: Data Engineer | B44: Data Engineer | C44: Anywhere | D44: Full-time | E44: True | F44: United States | G44: 45208.563 | H44: 190000 | I44: FirstParty | J44: ['sql', 'python', 'r', 'aws', 'airflow', 'matplotlib', 'plotly', 'ggplot2', 'linux', 'tableau', 'looker']
A45: Machine Learning Engineer | B45: Computer Vision Developer (R&D) | C45: Bengaluru, Karnataka, India | D45: Full-time | E45: False | F45: India | G45: 44975.55 | H45: 79200 | I45: Bosch Group | J45: ['python', 'opencv', 'tensorflow', 'pytorch', 'keras', 'mxnet']
A46: Senior Data Engineer | B46: Senior Software (Data) Engineer - Advanced Robotic Factory Machine... | C46: Anywhere | D46: Full-time | E46: True | F46: United States | G46: 44999.576 | H46: 190000 | I46: TEEMA | J46: ['python', 'kafka', 'django']
A47: Data Scientist | B47: Data Scientist | C47: Minneapolis, MN | D47: Full-time | E47: False | F47: United States | G47: 44978.559 | H47: 70700 | I47: Target | J47: ['java', 'scala', 'python', 'r', 'kotlin', 'sql', 'spark']
A48: Senior Data Engineer | B48: Senior Data Engineer - SQL, Snowflake | C48: Anywhere | D48: Full-time | E48: True | F48: United States | G48: 45058.561 | H48: 180000 | I48: CyberCoders | J48: ['sql', 'python', 'snowflake', 'redshift', 'aws', 'pandas']
A49: Software Engineer | B49: Senior Software Engineer - Live Streaming Infrastructure - Data... | C49: Mountain View, CA | D49: Full-time | E49: False | F49: United States | G49: 45116.545 | H49: 233500 | I49: TikTok | J49: ['c', 'c++', 'java', 'python', 'go', 'hadoop', 'spark', 'kafka']
A50: Data Engineer | B50: Sr. Data Engineer | C50: Indianapolis, IN | D50: Full-time | E50: False | F50: United States | G50: 45097.547 | H50: 102500 | I50: Insight Global | J50: ['sql', 'powershell', 'azure', 'snowflake', 'spark', 'git']
A51: Data Engineer | B51: Staff Data Engineer | C51: Tel Aviv-Yafo, Israel | D51: Full-time | E51: False | F51: Israel | G51: 45170.58 | H51: 79200 | I51: DoubleVerify | J51: ['python', 'scala', 'sql', 'java', 'gcp', 'databricks', 'bigquery', 'spark', 'kafka', 'docker', 'kubernetes', 'gitlab']
A52: Data Engineer | B52: Data Engineer, Analytics (Generalist) | C52: Des Moines, IA | D52: Full-time | E52: False | F52: United States | G52: 45030.563 | H52: 198500 | I52: Meta | J52: ['sql', 'python']
... A61: Data Analyst | B61: Sr Data Analyst | C61: Long Beach, CA | D61: Full-time | E61: False | F61: United States | G61: 44973.542 | H61: 89111.75 | I61: Molina Healthcare | J61: ['excel']
A62: Data Engineer | B62: Data Engineer – Top Secret Security Clearance | C62: New York, NY | D62: Full-time | E62: False | F62: Sudan | G62: 45250.572 | H62: 160000 | I62: Alldus
A63: Data Analyst | B63: Data Analyst | C63: Irvine, CA | D63: Full-time | E63: False | F63: United States | G63: 45008.543 | H63: 111175 | I63: Western Digital | J63: ['sql', 'tableau', 'power bi', 'excel']
A64: Data Analyst | B64: Data Analyst - Data17829 | C64: Tampa, FL | D64: Full-time | E64: False | F64: United States | G64: 45125.543 | H64: 120000 | I64: Acrisure | J64: ['shell', 'sql', 'azure', 'databricks', 'linux']
A65: Data Engineer | B65: Data Engineer | C65: Anywhere | D65: Full-time | E65: True | F65: Sudan | G65: 45027.619 | H65: 200000 | I65: Vibrant Planet | J65: ['python', 'airflow', 'hadoop', 'spark', 'pandas', 'jupyter']
A66: Data Analyst | B66: Data Integration Analyst (West Coast/Chicago) | C66: Chicago, IL | D66: Full-time | E66: False | F66: United States | G66: 45125.543 | H66: 101500 | I66: Forsta | J66: ['php', 'python', 'express']
A67: Data Engineer | B67: Quant/Data Engineer - Macro Trading Pod - Hedge Fund - $350k | D67: Full-time | E67: False | F67: United States | G67: 45209.548 | H67: 175000 | I67: Paragon Executive Intelligence | J67: ['python', 'sql', 'airflow']
A68: Data Engineer | B68: Data Engineer | C68: Jacksonville Beach, FL | D68: Full-time | E68: False | F68: United States | G68: 45227.566 | H68: 140000 | I68: Ascendo Resources | J68: ['sql', 'python', 'azure', 'github']
A69: Data Engineer | B69: Data Engineer - SQL (Power BI) | C69: India | D69: Full-time | E69: False | F69: India | G69: 45230.549 | H69: 156500 | I69: Gartner | J69: ['java', 't-sql', 'sql', 'azure', 'power bi', 'dax', 'notion']
A70: Data Engineer | B70: Data Engineer | C70: Mossville, IL | D70: Full-time | E70: False | F70: United States | G70: 45189.547 | H70: 82500 | I70: HCLTech
A71: Senior Data Scientist | B71: Senior Data Scientist | C71: Atlanta, GA | D71: Full-time | E71: False | F71: United States | G71: 45082.546 | H71: 120000 | I71: Brooksource | J71: ['r', 'python', 'sas', 'sas', 'aws', 'azure', 'gcp', 'hadoop', 'spark']
A72: Senior Data Scientist | B72: Senior Data Scientist | C72: Waltham, MA | D72: Full-time | E72: False | F72: United States | G72: 45257.544 | H72: 112500 | I72: hackajob | J72: ['r', 'python', 'sql', 'excel']
A73: Business Analyst | B73: Business Analyst to support Channel Engagement team in data analysis | C73: Sweden | D73: Full-time | E73: False | F73: Sweden | G73: 45289.553 | H73: 43200 | I73: Nordea | J73: ['qlik']
A74: Data Engineer | B74: Data Engineer | C74: Murfreesboro, TN | D74: Full-time | E74: False | F74: United States | G74: 45030.563 | H74: 141000 | I74: Middle Tennessee EMC | J74: ['python', 'java', 'sql', 'aws', 'azure']
A75: Data Engineer | B75: Data Engineer | C75: Anywhere | D75: Full-time | E75: True | F75: Sudan | G75: 44935.566 | H75: 140000 | I75: Robert Half | J75: ['python', 'sql', 'java', 't-sql', 'oracle', 'spark', 'pyspark', 'kafka', 'airflow', 'linux', 'sap', 'github']
A76: Data Engineer | B76: Data Engineer | C76: Cincinnati, OH | D76: Full-time | E76: False | F76: United States | G76: 45182.547 | H76: 85000 | I76: Pomeroy Technologies, LLC.
A77: Senior Data Engineer | B77: Senior Director, Data Engineering | C77: Dublin, CA | D77: Full-time | E77: False | F77: United States | G77: 45182.547 | H77: 147500 | I77: Snowflake Inc. | J77: ['sql', 'python', 'snowflake', 'aws', 'azure', 'gcp']
A78: Data Scientist | B78: Data Scientist | C78: Anywhere | D78: Full-time | E78: True | F78: United States | G78: 45040.544 | H78: 95000 | I78: Meduit | Driving Revenue Cycle Performance | J78: ['sql', 'python']
A79: Data Scientist | B79: Staff Data Scientist, New Initiatives - Remote | C79: Boston, MA | D79: Full-time | E79: False | F79: United States | G79: 45143.555 | H79: 206500 | I79: Dropbox | J79: ['sql', 'python']
A80: Data Engineer | B80: Data Engineer - Quant Hedge Fund | D80: Full-time | E80: False | F80: United States | G80: 45281.547 | H80: 300000 | I80: Capital Markets Recruitment | J80: ['python', 'sql', 'nosql', 'aws']
A81: Data Scientist | B81: Sr. Data Scientist- Consumer Deposits & Small Business | C81: Dania Beach, FL | D81: Full-time | E81: False | F81: United States | G81: 45041.545 | H81: 140062.5 | I81: Santander Holdings USA Inc | J81: ['sas', 'sas', 'sql', 'python', 'r']
A82: Data Scientist | B82: User Growth Data Scientist, E-Commerce- USDS | C82: Mountain View, CA | D82: Full-time | E82: False | F82: United States | G82: 45073.542 | H82: 101821.5 | I82: TikTok | J82: ['express']
A83: Data Engineer | B83: Data Engineer | C83: Portland, OR | D83: Full-time | E83: False | F83: United States | G83: 45126.548 | H83: 145000 | I83: Insight Global | J83: ['python', 'r', 'java', 'azure', 'aws', 'snowflake', 'hadoop', 'kafka', 'spark']
A84: Data Analyst | B84: Data Analyst | C84: Midland, TX | D84: Full-time | E84: False | F84: Sudan | G84: 45163.57 | H84: 70000 | I84: Advanced Stimulation Technologies, Inc | J84: ['c', 'outlook', 'word', 'excel', 'powerpoint']
A85: Data Analyst | B85: Data Analytics- Auto Intern | C85: Dublin, CA | D85: Internship | E85: False | F85: United States | G85: 45287.543 | H85: 35000 | I85: Epicor | J85: ['go']
A86: Data Engineer | B86: Data Engineer/ Scientist- (Data Governance) | C86: Cincinnati, OH | D86: Full-time | E86: False | F86: United States | G86: 45208.56 | H86: 90000 | I86: Prodware Solutions | J86: ['oracle']
A87: Data Scientist | B87: Analyst II, Ancillary Revenue Data Scientist (Remote Work... | C87: Anywhere | D87: Full-time | E87: True | F87: United States | G87: 44970.546 | H87: 75465 | I87: Frontier Airlines | J87: ['python', 'sql']
A88: Senior Data Engineer | B88: Energy Storage Senior Data Engineer (REMOTE) | C88: Anywhere | D88: Full-time | E88: True | F88: United States | G88: 45155.548 | H88: 135000 | I88: Jobot | J88: ['python', 'aws', 'redshift', 'flow', 'terraform', 'ansible', 'puppet']
A89: Data Analyst | B89: Admin & Data Analyst | C89: United Kingdom | D89: Full-time | E89: False | F89: United Kingdom | G89: 44967.58 | H89: 51014 | I89: Catch22 | J89: ['excel', 'word', 'outlook']
A90: Senior Data Engineer | B90: Senior Data Engineer | C90: Sunnyvale, CA | D90: Full-time | E90: False | F90: United States | G90: 45085.561 | H90: 160000 | I90: Storm2 | J90: ['java', 'sql', 'mongodb', 'mongodb', 'aws', 'redshift', 'aurora', 'node']
A91: Data Engineer | B91: VP, Lead BI/ Data Engineer | C91: Dallas, TX | D91: Full-time | E91: False | F91: United States | G91: 45013.551 | H91: 177500 | I91: Aegistech | J91: ['java', 'oracle', 'tableau', 'flow']
A92: Business Analyst | B92: BI Analyst | C92: South Africa | D92: Full-time | E92: False | F92: South Africa | G92: 45270.551 | H92: 130000 | I92: Nedbank | J92: ['sql']
A93: Senior Data Analyst | B93: Sr. Marketing Data Analyst | C93: Anywhere | D93: Full-time | E93: True | F93: United States | G93: 45047.543 | H93: 170000 | I93: CyberCoders
A94: Data Engineer | B94: Data Engineer / Data Governance | C94: Sunnyvale, CA | D94: Full-time | E94: False | F94: Sudan | G94: 45076.572 | H94: 125000 | I94: Purple Drive Technologies | J94: ['mysql', 'neo4j', 'snowflake']
A95: Senior Data Engineer | B95: Senior Data Engineer | C95: Fair Oaks, CA | D95: Full-time | E95: False | F95: United States | G95: 45125.547 | H95: 131100 | I95: 84.51 | J95: ['sql', 'python', 'java', 'scala', 'databricks', 'azure', 'snowflake', 'hadoop', 'spark', 'kafka', 'tableau', 'power bi', 'cognos', 'github']
A96: Data Scientist | B96: Data Scientist Mid-Level | C96: Charlotte, NC | D96: Full-time | E96: False | F96: United States | G96: 45181.587 | H96: 138640 | I96: USAA | J96: ['python', 'r', 'sql', 'nosql', 'gitlab']
A97: Data Engineer | B97: Lead Data Engineer | C97: Anywhere | D97: Full-time | E97: True | F97: United States | G97: 45041.546 | H97: 150000 | I97: CyberCoders | J97: ['sql', 'hadoop', 'spark', 'kafka', 'flow']
A98: Senior Data Engineer | B98: Senior Data Engineer | C98: Hockessin, DE | D98: Full-time | E98: False | F98: United States | G98: 44983.564 | H98: 173500 | I98: Capital One | J98: ['scala', 'python', 'nosql', 'mongo', 'shell', 'mysql', 'cassandra', 'redshift', 'snowflake', 'aws', 'azure', 'hadoop', 'kafka', 'spark']
A99: Data Engineer | B99: Staff Software Engineer - Data Engineering (Java/Spark) | C99: Bengaluru, Karnataka, India | D99: Full-time | E99: False | F99: India | G99: 45072.551 | H99: 147500 | I99: Zscaler | J99: ['java', 'nosql', 'neo4j', 'redshift', 'aws', 'spring', 'spark', 'excel', 'jenkins']
A100: Senior Data Scientist | B100: Senior Data Scientist | C100: Anywhere | D100: Full-time | E100: True | F100: United States | G100: 45049.545 | H100: 170000 | I100: Harnham | J100: ['python', 'sql']
A101: Data Analyst | B101: Senior Threat Intelligence & Data analyst | C101: Tel Aviv-Yafo, Israel | D101: Full-time | E101: False | F101: Israel | G101: 45112.566 | H101: 111175 | I101: Armis Security | J101: ['python']
A102: Data Scientist | B102: Marketing Data Scientist | C102: Anywhere | D102: Contractor | E102: True | F102: United States | G102: 44927.596 | H102: 113000 | I102: Stefanini, Inc | J102: ['python', 'r', 'azure', 'databricks', 'aws', 'tableau', 'power bi']
A103: Business Analyst | B103: BI Analyst | C103: Orlando, FL | D103: Full-time | E103: False | F103: United States | G103: 45112.544 | H103: 85000 | I103: Hays | J103: ['sql', 'tableau']
A104: Data Scientist | B104: Data Scientist | C104: New York, NY | D104: Full-time | E104: False | F104: United States | G104: 45033.543 | H104: 140000 | I104: Prohires | J104: ['python', 'java', 'r', 'sas', 'sas', 'sql', 'sql server', 'db2', 'oracle']
A105: Senior Data Engineer | B105: Senior Data Scientist Engineer | C105: Bulgaria | D105: Full-time | E105: False | F105: Bulgaria | G105: 45269.554 | H105: 170500 | I105: SAP | J105: ['python', 'aws', 'azure', 'jupyter', 'numpy', 'pandas', 'keras', 'scikit-learn', 'tensorflow', 'pytorch', 'flask', 'django', 'fastapi', 'sap', 'docker', 'kubernetes', 'github']
... A118: Business Analyst | B118: Financial Business Intelligence Analyst | C118: Georgia | D118: Full-time | E118: False | F118: United States | G118: 45196.6 | H118: 87500 | I118: Franklin Fitch | J118: ['sql', 'tableau', 'power bi', 'excel', 'ssrs', 'powerpoint']
A119: Data Engineer | B119: Lead Data Engineer | C119: Tennessee | D119: Full-time | E119: False | F119: United States | G119: 44951.559 | H119: 125000 | I119: MFM Search LLC
A120: Senior Data Analyst | B120: Senior Analyst Data Visualization | C120: San Antonio, TX | D120: Full-time | E120: False | F120: United States | G120: 45199.543 | H120: 87500 | I120: Z&A Recruiting | J120: ['tableau', 'alteryx', 'outlook']
A121: Data Scientist | B121: Data Scientist | C121: Anywhere | D121: Full-time | E121: True | F121: United States | G121: 45051.555 | H121: 170000 | I121: CyberCoders | J121: ['python', 'azure', 'pytorch', 'tensorflow', 'opencv', 'datarobot']
A122: Data Engineer | B122: Senior Associate, Azure Data Engineer | C122: Orlando, FL | D122: Full-time | E122: False | F122: United States | G122: 44943.549 | H122: 90000 | I122: KPMG | J122: ['sql', 'go', 'sql server', 'azure', 'databricks', 'pyspark', 'flow', 'github']
...

Sheet Monthly Pivot
A3: Row Labels | B3: Job Postings | C3: Average Salary
A4: Jan | B4: 2296 | C4: 123007.42
A5: Feb | B5: 2010 | C5: 122913.93
A6: Mar | B6: 2204 | C6: 122947.81
A7: Apr | B7: 1876 | C7: 121856.55
A8: May | B8: 1911 | C8: 123656.75
A9: Jun | B9: 2331 | C9: 124321.14
A10: Jul | B10: 2219 | C10: 123470.57
A11: Aug | B11: 2095 | C11: 125819.43
A12: Sep | B12: 1245 | C12: 125251.28
A13: Oct | B13: 1310 | C13: 124606.65
A14: Nov | B14: 1124 | C14: 119817.18
A15: Dec | B15: 1381 | C15: 120199.42
A16: Grand Total | B16: 22002 | C16: 123287.79

Sheet Sheet6
A1: ﻿job_title_short | B1: job_title | C1: job_location | D1: job_schedule_type | E1: job_work_from_home | F1: job_country | G1: job_posted_date | H1: salary_year_avg | I1: company_name | J1: job_skills
A2: Data Analyst | B2: Data Analyst | C2: Lisbon, Portugal | D2: Full-time | E2: False | F2: Portugal | G2: 45084.271 | H2: 111175 | I2: Farfetch | J2: ['sql', 'python', 'r', 'looker']
A3: Data Engineer | B3: Data Engineer | C3: Arlington, VA | D3: Full-time | E3: False | F3: Sudan | G3: 45103.599 | H3: 140000 | I3: Intelletec | J3: ['mongodb', 'mongodb', 'python', 'r', 'sql', 'mysql', 'mariadb', 'oracle', 'spark', 'tableau', 'kubernetes']
A4: Data Scientist | B4: Data Scientist | C4: Islamabad, Pakistan | D4: Contractor | E4: False | F4: Pakistan | G4: 45084.262 | H4: 157500 | I4: Inbox Business Technologies | J4: ['sql', 'python', 'r', 'hadoop']
A5: Senior Data Engineer | B5: Senior Data Engineer | C5: San Francisco, CA | D5: Full-time | E5: False | F5: United States | G5: 45105.253 | H5: 147500 | I5: Kikoff | J5: ['nosql', 'python', 'hadoop', 'spark']
A6: Data Analyst | B6: Recruitment Data Analyst | C6: Mumbai, Maharashtra, India | D6: Full-time | E6: False | F6: India | G6: 45084.257 | H6: 111175 | I6: Framestore | J6: ['power bi', 'tableau']
A7: Data Analyst | B7: Lead Credit Bureau Data Analyst | C7: Des Plaines, IL | D7: Full-time | E7: False | F7: United States | G7: 45079.251 | H7: 115000 | I7: Discover Financial Services | J7: ['unix']
A8: Senior Data Scientist | B8: Senior Data Scientist | C8: Bengaluru, Karnataka, India | D8: Full-time | E8: False | F8: India | G8: 45104.258 | H8: 157500 | I8: Publicis Groupe | J8: ['aws', 'spark', 'tableau', 'cognos', 'excel', 'powerpoint', 'power bi', 'looker', 'jira']
A9: Data Analyst | B9: Data Analyst / Business Intelligence Specialist | C9: Katowice, Poland | D9: Full-time | E9: False | F9: Poland | G9: 45107.294 | H9: 57500 | I9: SGS | J9: ['python', 'power bi']
A10: Data Scientist | B10: NATOIS-0008 Data Scientist (NS) - TUE 13 Jun | C10: Brussels, Belgium | D10: Full-time | E10: False | F10: Belgium | G10: 45082.581 | H10: 157500 | I10: EMW, Inc. | J10: ['c', 'r', 'sql', 'python', 'aws', 'azure', 'hadoop', 'tableau']
A11: Senior Data Analyst | B11: Senior Data Analyst (Flights team, Bangkok-based, Relocation provided) | C11: Bangkok, Thailand | D11: Full-time | E11: False | F11: Thailand | G11: 45087.264 | H11: 111175 | I11: Agoda | J11: ['sql', 'python', 'r', 'tableau', 'excel']
A12: Machine Learning Engineer | B12: Machine Learning Engineer | C12: Berlin, Germany | D12: Full-time | E12: False | F12: Germany | G12: 45087.263 | H12: 166000 | I12: PlayStation Global | J12: ['aws', 'pandas', 'numpy', 'tensorflow', 'pytorch', 'linux', 'git', 'docker', 'kubernetes']
A13: Data Engineer | B13: Drug Discovery Informatics Data Engineer, Hyderabad | C13: Hyderabad, Telangana, India | D13: Full-time | E13: False | F13: India | G13: 45104.259 | H13: 147500 | I13: Schrödinger | J13: ['python', 'sql', 'airflow', 'git', 'svn', 'docker', 'kubernetes']
... A19: Senior Data Scientist | B19: Senior Data Scientist (Remote) | C19: Anywhere | D19: Full-time | E19: True | F19: Sudan | G19: 45090.273 | H19: 166500 | I19: Billtrust | J19: ['sql', 'python', 'jupyter', 'pytorch', 'tensorflow', 'linux', 'git', 'jenkins']
A20: Data Scientist | B20: Data Science Director, Instagram - Product Foundation | C20: Menlo Park, CA | D20: Full-time | E20: False | F20: United States | G20: 45105.211 | H20: 243000 | I20: Facebook
A21: Senior Data Engineer | B21: Senior Data Engineer, AdSmart (Scala) | C21: New York, NY | D21: Full-time | E21: False | F21: United States | G21: 45102.218 | H21: 132500 | I21: NBCUniversal | J21: ['scala', 'java', 'sql', 'nosql', 'aws', 'spark', 'kafka', 'kubernetes']
A22: Business Analyst | B22: Lead BI Analyst (Supply Analytics, Bangkok-based) | C22: Bangkok, Thailand | D22: Full-time | E22: False | F22: Thailand | G22: 45087.222 | H22: 63000 | I22: Agoda | J22: ['sql', 'tableau']
A23: Data Scientist | B23: Manager - Data Science | C23: Phoenix, AZ | D23: Full-time | E23: False | F23: Sudan | G23: 45104.265 | H23: 115000 | I23: American Express | J23: ['python', 'r', 'sql', 'pandas', 'numpy', 'tensorflow', 'scikit-learn', 'express', 'tableau', 'power bi']
A24: Senior Data Engineer | B24: Senior Data Engineer, AWS Global Trade and Product Compliance... | C24: New York, NY | D24: Full-time | E24: False | F24: Sudan | G24: 45100.25 | H24: 150000 | I24: Amazon | J24: ['python', 'sql', 'java', 'scala', 'typescript', 'aws', 'redshift', 'spark', 'hadoop', 'flow']
A25: Business Analyst | B25: Senior Business Intelligence Engineer | C25: Lagos, Nigeria | D25: Full-time | E25: False | F25: Nigeria | G25: 45078.23 | H25: 99150 | I25: Lemonade Finance | J25: ['sql', 'bigquery', 'redshift', 'tableau']
A26: Data Engineer | B26: Data Engineer – Oracle | C26: Jucu, Romania | D26: Full-time | E26: False | F26: Romania | G26: 45097.236 | H26: 134241 | I26: Bosch Group | J26: ['sql', 'oracle', 'azure', 'hadoop', 'spark', 'airflow', 'gdpr', 'tableau', 'power bi', 'ssis', 'jira']
A27: Machine Learning Engineer | B27: Machine Learning Engineer | C27: Cairo, Egypt | D27: Full-time | E27: False | F27: Egypt | G27: 45083.076 | H27: 166000 | I27: Unifonic | J27: ['python', 'sql', 'numpy', 'pandas', 'pyspark', 'scikit-learn', 'tensorflow', 'pytorch', 'keras', 'linux', 'git', 'jira']
A28: Data Scientist | B28: Staff Data Scientist, Advanced Analytics (Remote). Job in Dallas... | C28: Dallas, TX | D28: Full-time | E28: False | F28: Sudan | G28: 45080.093 | H28: 181000 | I28: Drata | J28: ['sql', 'tableau', 'power bi']
A29: Data Scientist | B29: Data Scientist, Machine Learning | C29: New York, NY | D29: Full-time | E29: False | F29: United States | G29: 45093.054 | H29: 170000 | I29: Harnham
A30: Data Engineer | B30: Data Engineer (H/F) | C30: Toulouse, France | D30: Full-time | E30: False | F30: France | G30: 45078.062 | H30: 134241 | I30: Meritis
A31: Data Engineer | B31: Data Engineer, Big Data Privacy and Security | C31: San Jose, CA | D31: Full-time | E31: False | F31: Sudan | G31: 45095.569 | H31: 171000 | I31: TikTok | J31: ['spark', 'kafka']
A32: Data Scientist | B32: Tech Excellence Data Scientist, Junior | C32: Colorado Springs, CO | D32: Full-time | E32: False | F32: Sudan | G32: 45092.099 | H32: 95650 | I32: Booz Allen Hamilton | J32: ['python', 'r', 'sql', 'aws', 'azure', 'scikit-learn', 'keras', 'tensorflow', 'pytorch', 'tableau', 'qlik', 'power bi', 'github']
A33: Data Scientist | B33: Data Scientist II -AI/ML (remote) | C33: Anywhere | D33: Full-time | E33: True | F33: United States | G33: 45104.044 | H33: 134500 | I33: MultiPlan Inc. | J33: ['python', 'r', 'sql']
A34: Data Analyst | B34: Data Analyst | C34: San Francisco, CA | D34: Full-time | E34: False | F34: United States | G34: 45104.042 | H34: 137000 | I34: FLYR Labs | J34: ['sql', 'python', 'c', 'airflow', 'looker', 'tableau', 'git']
A35: Data Scientist | B35: Data Scientist, In-car Ads | C35: New York, NY | D35: Full-time | E35: False | F35: United States | G35: 45080.044 | H35: 147500 | I35: Lyft | J35: ['sql', 'python', 'r']
A36: Data Engineer | B36: Data Engineer | C36: Chennai, Tamil Nadu, India | D36: Full-time | E36: False | F36: India | G36: 45104.05 | H36: 147500 | I36: Smartek21.com | J36: ['python', 'sql', 'java', 'mongodb', 'mongodb', 'scala', 'mysql', 'postgresql', 'spark', 'airflow']
A37: Data Scientist | B37: Lead Data Scientist | C37: Atlanta, GA | D37: Full-time | E37: False | F37: United States | G37: 45094.056 | H37: 170000 | I37: Harnham | J37: ['sql', 'r', 'python']
A38: Data Scientist | B38: Data Scientist (Remote) | C38: Anywhere | D38: Full-time | E38: True | F38: United States | G38: 45104.044 | H38: 109844 | I38: Niagara Bottling | J38: ['sql', 'python', 'r', 'tensorflow', 'keras', 'scikit-learn', 'excel']
A39: Data Scientist | B39: Staff Data Scientist | C39: Illinois | D39: Full-time | E39: False | F39: United States | G39: 45087.044 | H39: 124000 | I39: Kraft Heinz Company | J39: ['python', 'r', 'snowflake', 'azure', 'aws', 'spark', 'hadoop']
A40: Machine Learning Engineer | B40: Head of AML Operations (m/f/d) | C40: Ballerup, Denmark | D40: Full-time | E40: False | F40: Denmark | G40: 45091.559 | H40: 105300 | I40: Nets
A41: Data Scientist | B41: Data Scientist | C41: Denver, CO | D41: Full-time | E41: False | F41: Sudan | G41: 45104.098 | H41: 120000 | I41: Project Canary, PBC | J41: ['python', 'c#', 'java']
A42: Data Scientist | B42: Data Scientist, Customer AI Engineering | C42: London, UK | D42: Full-time | E42: False | F42: United Kingdom | G42: 45097.551 | H42: 157500 | I42: Tractable | J42: ['python', 'numpy', 'pandas', 'scikit-learn']
A43: Data Analyst | B43: Data Analyst (Probationary) | C43: Port Washington, NY | D43: Full-time | E43: False | F43: United States | G43: 45086.042 | H43: 104500 | I43: Port Washington
A44: Data Analyst | B44: Data Analyst, Marketing | C44: San Francisco, CA | D44: Full-time | E44: False | F44: United States | G44: 45094.042 | H44: 167500 | I44: Notion | J44: ['sql', 'python', 'r', 'excel', 'tableau', 'looker', 'notion']
A45: Senior Data Engineer | B45: Senior Data Engineer in FinTech ($85k-$135k) | C45: Fort Worth, TX | D45: Full-time | E45: False | F45: United States | G45: 45087.046 | H45: 112500 | I45: CyberCoders | J45: ['sql', 'python', 'javascript', 'c#', 'snowflake', 'bigquery', 'redshift', 'ssis', 'tableau']
A46: Data Scientist | B46: Data Scientist | C46: San Francisco, CA | D46: Full-time | E46: False | F46: United States | G46: 45104.044 | H46: 143000 | I46: FLYR Labs | J46: ['python', 'c', 'tensorflow']
A47: Data Analyst | B47: Data Analyst | C47: United States | D47: Full-time | E47: False | F47: Sudan | G47: 45098.083 | H47: 100500 | I47: Govini | J47: ['python', 'r']
A48: Data Scientist | B48: Data Scientist (Real-time Ops) | C48: Walnut Creek, CA | D48: Full-time | E48: False | F48: United States | G48: 45092.044 | H48: 70000 | I48: Gridware | J48: ['python', 'linux', 'git']
A49: Machine Learning Engineer | B49: Machine Learning Engineer | C49: Cluj-Napoca, Romania | D49: Full-time | E49: False | F49: Romania | G49: 45100.08 | H49: 166000 | I49: Connatix | J49: ['python', 'aws', 'docker']
A50: Data Engineer | B50: Sr. Data Engineer | C50: Indianapolis, IN | D50: Full-time | E50: False | F50: United States | G50: 45097.547 | H50: 102500 | I50: Insight Global | J50: ['sql', 'powershell', 'azure', 'snowflake', 'spark', 'git']
A51: Data Engineer | B51: Azure Data Engineer | C51: Toronto, ON, Canada | D51: Full-time | E51: False | F51: Canada | G51: 45087.051 | H51: 80850 | I51: Aviso Wealth | J51: ['azure', 'aws', 'snowflake', 'databricks', 'oracle', 'hadoop', 'ssis']
A52: Data Scientist | B52: Modeling and Simulation Data Scientist | C52: Dahlgren, VA | D52: Full-time | E52: False | F52: United States | G52: 45107.092 | H52: 115000 | I52: Booz Allen Hamilton | J52: ['r', 'python', 'sql', 'nosql', 'plotly', 'seaborn', 'ggplot2']
A53: Data Analyst | B53: Institution Data Analyst | C53: Singapore | D53: Full-time | E53: False | F53: Singapore | G53: 45090.084 | H53: 57500 | I53: OKX | J53: ['r']
A54: Data Scientist | B54: Data Scientist | C54: Washington, DC | D54: Full-time | E54: False | F54: United States | G54: 45093.055 | H54: 115000 | I54: Booz Allen Hamilton
A55: Data Scientist | B55: Scientist 4, Data Science | C55: Thailand | D55: Full-time | E55: False | F55: Thailand | G55: 45101.062 | H55: 79200 | I55: Western Digital | J55: ['sql', 'r', 'python', 'java', 'aws', 'hadoop', 'spark']
A56: Data Engineer | B56: Systems Engineer IV - Data Engineer (Hybrid) (Greater Denver Area, CO) | C56: Denver, CO | D56: Full-time | E56: False | F56: United States | G56: 45107.049 | H56: 122600 | I56: Spectrum | J56: ['python', 'sql', 'hadoop', 'spark', 'pyspark']
A57: Senior Data Scientist | B57: Senior Data Scientist | C57: Anywhere | D57: Full-time | E57: True | F57: Sudan | G57: 45091.599 | H57: 160000 | I57: Summit Consulting, LLC | J57: ['r', 'python']
A58: Data Analyst | B58: SCHOOL DATA ANALYST | C58: Greenwood Lake, NY | D58: Full-time | E58: False | F58: United States | G58: 45084.042 | H58: 71000 | I58: Greenwood Lake UFSD | J58: ['spreadsheet']
A59: Data Analyst | B59: Data Analyst / Data Scientist, Wholesale | C59: Dallas, TX | D59: Full-time | E59: False | F59: Sudan | G59: 45106.101 | H59: 118965 | I59: Frontier Communications | J59: ['python', 'pandas', 'excel', 'alteryx']
A60: Data Scientist | B60: Lead Data Scientist | C60: San Francisco, CA | D60: Full-time | E60: False | F60: United States | G60: 45079.059 | H60: 216000 | I60: Cisco | J60: ['python', 'r', 'sql', 'aws']
A61: Data Scientist | B61: Data Scientist | C61: Budapest, Hungary | D61: Full-time | E61: False | F61: Hungary | G61: 45079.08 | H61: 157500 | I61: Lynx Analytics | J61: ['python', 'r', 'sas', 'sas', 'c', 'java', 'sap']
A62: Data Engineer | B62: Staff Data Engineer | C62: Anywhere | D62: Full-time | E62: True | F62: United States | G62: 45087.061 | H62: 180000 | I62: CyberCoders | J62: ['python', 'go', 'scala', 'sql', 'javascript', 'typescript', 'databricks', 'snowflake', 'aws', 'azure', 'gcp', 'airflow', 'kafka', 'spark', 'graphql', 'react', 'pandas', 'docker', 'kubernetes', 'terraform']
A63: Data Scientist | B63: Data Scientist | C63: Springfield, VA | D63: Full-time | E63: False | F63: United States | G63: 45106.044 | H63: 132500 | I63: Parsons Corporation | J63: ['python', 'java', 'sql', 'cassandra', 'hadoop', 'spark', 'tableau']
A64: Data Engineer | B64: Data Engineer | C64: Bengaluru, Karnataka, India | D64: Full-time | E64: False | F64: India | G64: 45106.066 | H64: 147500 | I64: Rockstar Games | J64: ['sql', 't-sql', 'python', 'scala', 'java', 'shell', 'cassandra', 'snowflake', 'azure', 'databricks', 'kafka', 'spark', 'hadoop', 'airflow', 'scikit-learn', 'jupyter', 'linux']
A65: Machine Learning Engineer | B65: DevOPS/ MLOPs Engineer | C65: Tel Aviv-Yafo, Israel | D65: Full-time | E65: False | F65: Israel | G65: 45078.084 | H65: 64800 | I65: Eleos Health | J65: ['python', 'r', 'aws', 'gcp', 'azure', 'tensorflow', 'pytorch', 'scikit-learn', 'linux']
A66: Data Scientist | B66: Staff Data Scientist, Advanced Analytics (Remote) | C66: San Diego, CA | D66: Full-time | E66: False | F66: United States | G66: 45096.044 | H66: 181000 | I66: Drata | J66: ['sql', 'tableau', 'power bi']
... A72: Senior Data Analyst | B72: Senior Healthcare Data Analyst | C72: Middletown, RI | D72: Full-time | E72: False | F72: United States | G72: 45085.834 | H72: 86500 | I72: newport county community health | J72: ['sql', 'power bi', 'planner']
A73: Data Analyst | B73: Systems Analyst- Data Control Center | C73: Lompoc, CA | D73: Full-time | E73: False | F73: United States | G73: 45092.834 | H73: 92088 | I73: Craig Technologies
A74: Data Scientist | B74: Data Scientist | C74: Pune, Maharashtra, India | D74: Full-time | E74: False | F74: India | G74: 45089.854 | H74: 70000 | I74: Avaloq | J74: ['python', 'r', 'sql', 'java', 'mysql', 'sql server', 'redshift', 'aws', 'azure', 'oracle', 'tableau', 'power bi', 'kubernetes', 'docker', 'git', 'jenkins']
A75: Data Analyst | B75: Transportation Data Analyst | C75: Sacramento, CA | D75: Full-time | E75: False | F75: United States | G75: 45083.834 | H75: 57500 | I75: ZERO EMISSIONS PARTNERS LLC | J75: ['excel']
A76: Senior Data Analyst | B76: Sr. Data Scientist, Analytics | C76: Los Angeles, CA | D76: Full-time | E76: False | F76: United States | G76: 45083.836 | H76: 182500 | I76: Quizlet | J76: ['go', 'sql', 'python', 'airflow']
A77: Data Engineer | B77: Senior Python / Data Engineer | C77: Anywhere | D77: Full-time | E77: True | F77: United States | G77: 45097.838 | H77: 110000 | I77: Adaptive Solutions Group | J77: ['python', 'scala', 'sql', 'databricks', 'azure', 'aws']
A78: Data Engineer | B78: Data Engineer/Data Modeler - Fully remote and Permanent | C78: Anywhere | D78: Full-time | E78: True | F78: United States | G78: 45082.869 | H78: 135000 | I78: Insight Global | J78: ['sql', 'azure', 'snowflake', 'pyspark']
A79: Data Analyst | B79: Data Analyst (Hybrid, 1+ yrs exp req) | C79: Rowlett, TX | D79: Full-time | E79: False | F79: United States | G79: 45091.834 | H79: 61000 | I79: #twiceasnice Recruiting | J79: ['excel', 'power bi']
A80: Data Analyst | B80: Data Analyst | C80: Roswell, GA | D80: Contractor | E80: False | F80: United States | G80: 45104.872 | H80: 117500 | I80: Staffing Technologies | J80: ['sql', 'python']
A81: Data Scientist | B81: Data Scientist (FAA) | C81: Washington, DC | D81: Full-time | E81: False | F81: United States | G81: 45099.836 | H81: 161500 | I81: Noblis | J81: ['r']
A82: Senior Data Engineer | B82: Senior Data Engineer | C82: Georgia | D82: Full-time | E82: False | F82: Sudan | G82: 45106.901 | H82: 157500 | I82: Bellwether Staffing Solutions | J82: ['sql', 'python', 'databricks']
A83: Data Engineer | B83: Technical Architect (Data Engineering) | C83: Canada | D83: Full-time | E83: False | F83: Canada | G83: 45099.842 | H83: 147500 | I83: 3Pillar Global | J83: ['aws', 'excel']
A84: Business Analyst | B84: Marketing Analyst | C84: Anywhere | D84: Full-time | E84: True | F84: United States | G84: 45095.834 | H84: 106000 | I84: Blend | J84: ['sql', 'excel']
A85: Data Analyst | B85: Data Analyst - Predictive Modeling | C85: Hartford, CT | D85: Full-time | E85: False | F85: United States | G85: 45086.833 | H85: 119200 | I85: CVS Health | J85: ['sql', 'python', 'hadoop', 'tableau']
... A93: Machine Learning Engineer | B93: Machine Learning Engineer | C93: Guadalajara, Jalisco, Mexico | D93: Full-time | E93: False | F93: Mexico | G93: 45098.863 | H93: 101029 | I93: Arrive Logistics | J93: ['python', 'azure', 'aws']
A94: Data Analyst | B94: Data Analyst | C94: Elgin, IL | D94: Contractor | E94: False | F94: United States | G94: 45089.834 | H94: 62500 | I94: Robert Half
A95: Data Analyst | B95: 8443- Data Analyst | C95: Jacksonville, FL | D95: Full-time | E95: False | F95: United States | G95: 45082.835 | H95: 102500 | I95: Interactive Resources - iR | J95: ['sql', 'python', 'aws', 'azure', 'gcp', 'oracle', 'power bi', 'excel', 'word', 'visio']
A96: Data Scientist | B96: Sr. Data Scientist | C96: Santiago, Chile | D96: Full-time | E96: False | F96: Chile | G96: 45105.885 | H96: 157500 | I96: Visa | J96: ['python', 'r', 'spark', 'scikit-learn', 'hadoop', 'tableau', 'power bi']
A97: Data Scientist | B97: Data Scientist | C97: Aberdeen Proving Ground, MD | D97: Full-time | E97: False | F97: United States | G97: 45104.836 | H97: 160000 | I97: CyberCoders | J97: ['python', 'java', 'c++']
A98: Data Analyst | B98: Data / Supply Chain Analyst | C98: Peachtree City, GA | D98: Full-time | E98: False | F98: United States | G98: 45078.892 | H98: 67500 | I98: Magnify | J98: ['excel']
A99: Data Scientist | B99: Lead Data Scientist | C99: Anywhere | D99: Contractor | E99: True | F99: Sudan | G99: 45089.898 | H99: 210000 | I99: Harnham | J99: ['go', 'sql', 'python', 'r']
A100: Senior Data Engineer | B100: Senior Data Engineer | C100: George Town, Penang, Malaysia | D100: Full-time | E100: False | F100: Malaysia | G100: 45089.858 | H100: 147500 | I100: Eurofins | J100: ['python', 'power bi', 'jenkins']
A101: Data Scientist | B101: Data Scientist (College) | C101: Anywhere | D101: Full-time | E101: True | F101: United States | G101: 45086.852 | H101: 67500 | I101: Customer Value Partners | J101: ['r', 'python', 'sql', 'excel']
A102: Data Analyst | B102: Budget Data Analyst (Power BI/Excel/VBA expert) | C102: Anywhere | D102: Full-time | E102: True | F102: United States | G102: 45097.835 | H102: 83000 | I102: General Dynamics Information Technology | J102: ['vba', 'sql', 'power bi', 'excel', 'word', 'flow']
A103: Senior Data Analyst | B103: Sr Clinical Data Analyst | C103: Philadelphia, PA | D103: Full-time | E103: False | F103: United States | G103: 45093.833 | H103: 102500 | I103: Xplora Search Group | J103: ['sql', 'power bi', 'ssrs']
A104: Data Scientist | B104: Data Scientist (Behavioral Health Claims Analysis) On site Columbia MD | C104: Columbia, MD | D104: Full-time | E104: False | F104: United States | G104: 45082.868 | H104: 110000 | I104: Internet of Things, LLC | J104: ['sql', 'python', 'r']
A105: Data Engineer | B105: Data Engineer | C105: Aurora, IL | D105: Full-time | E105: False | F105: Sudan | G105: 45083.862 | H105: 58926 | I105: Capital One | J105: ['scala', 'python', 'java', 'nosql', 'sql', 'mongo', 'shell', 'mysql', 'cassandra', 'redshift', 'snowflake', 'aws', 'azure', 'hadoop', 'kafka', 'spark']
A106: Senior Data Analyst | B106: Senior Data Analyst (Hedge Fund) | D106: Full-time | E106: False | F106: United States | G106: 45092.833 | H106: 170000 | I106: Mission Staffing | J106: ['sql', 'python', 'azure', 'flow']
A107: Senior Data Engineer | B107: Senior Azure Data Engineer | C107: Anywhere | D107: Full-time | E107: True | F107: Sudan | G107: 45093.606 | H107: 140000 | I107: eVigilant | J107: ['sql', 'azure', 'snowflake', 'databricks', 'aws']
A108: Senior Data Scientist | B108: Senior Data Scientist | C108: Bengaluru, Karnataka, India | D108: Full-time | E108: False | F108: India | G108: 45097.841 | H108: 157500 | I108: Zscaler | J108: ['python', 'sql', 'go', 'aws', 'azure', 'excel']
A109: Data Analyst | B109: Data Analyst | C109: Barcelona, Spain | D109: Full-time | E109: False | F109: Spain | G109: 45083.843 | H109: 100500 | I109: Coniq | J109: ['sql', 'python', 'mysql', 'tableau']
A110: Data Engineer | B110: Salesforce Data Engineer | C110: United States | D110: Full-time | E110: False | F110: United States | G110: 45104.856 | H110: 67500 | I110: Sedona Staffing Services | J110: ['go', 'sql']
A111: Data Scientist | B111: Senior Sales Specialist, AI Data Science | C111: Florida | D111: Full-time | E111: False | F111: United States | G111: 45097.836 | H111: 267875 | I111: NVIDIA | J111: ['spark', 'hadoop']
A112: Data Scientist | B112: Senior Analyst (Data Scientist) | C112: Washington, DC | D112: Full-time | E112: False | F112: United States | G112: 45085.835 | H112: 147500 | I112: Innovative Technology Partnerships LLC | J112: ['tableau', 'excel']
A113: Data Engineer | B113: Data Infrastructure Engineer | C113: Lisbon, Portugal | D113: Full-time | E113: False | F113: Portugal | G113: 45090.853 | H113: 80850 | I113: ComplyAdvantage | J113: ['sql', 'nosql', 'elasticsearch', 'aws', 'gcp', 'kafka', 'spark', 'kubernetes', 'terraform', 'docker', 'git']
A114: Data Engineer | B114: Data Engineer | C114: New York, NY | D114: Full-time | E114: False | F114: United States | G114: 45103.838 | H114: 125000 | I114: RWA.xyz | J114: ['spark']
A115: Data Scientist | B115: Data Scientist Specialist | C115: Pittsburgh, PA | D115: Full-time | E115: False | F115: United States | G115: 45090.835 | H115: 108000 | I115: BNY Mellon | J115: ['python', 'nosql', 'mongodb', 'mongodb', 'oracle', 'pandas', 'numpy']
A116: Data Scientist | B116: Data Scientist | C116: Wylie, TX | D116: Full-time | E116: False | F116: United States | G116: 45085.85 | H116: 128414.03 | I116: Dataline Communications, LLC | J116: ['c', 'c++', 'sql', 'python', 'r', 'matlab', 'spss']
A117: Data Analyst | B117: Data Management Lead Analyst (Hybrid) | C117: Jacksonville, FL | D117: Full-time | E117: False | F117: United States | G117: 45105.888 | H117: 137610 | I117: Citi
...

Sheet Salary Pivots
A2: Row Labels | B2: Average of salary_year_avg
A3: Business Analyst | B3: 91082.613
A4: Data Analyst | B4: 93842.613
A5: Cloud Engineer | B5: 111268.45
A6: Software Engineer | B6: 113393.76
A7: Senior Data Analyst | B7: 113911.36
A8: Machine Learning Engineer | B8: 126774.32
A9: Data Engineer | B9: 130125.6
A10: Data Scientist | B10: 135988.84
A11: Senior Data Engineer | B11: 145840.61
A12: Senior Data Scientist | B12: 154206.29
A13: Grand Total | B13: 123287.79
A16: Row Labels | B16: Average of salary_year_avg
A17: Non-Remote | B17: 121830.02
A18: Remote | B18: 131614.59
A19: Grand Total | B19: 123287.79

Sheet Salary Totals Pivot
A3: Row Labels | B3: Sum of salary_year_avg
A4: Business Analyst | B4: 4702761
A5: Cloud Engineer | B5: 271500
A6: Data Analyst | B6: 53951707
A7: Data Engineer | B7: 64154843
A8: Data Scientist | B8: 79677452
A9: Machine Learning Engineer | B9: 8106636
A10: Senior Data Analyst | B10: 17460399
A11: Senior Data Engineer | B11: 28733726
A12: Senior Data Scientist | B12: 28444499
A13: Software Engineer | B13: 4289044
A14: Grand Total | B14: 2.8979257e+08

Sheet Salary Distribution
A1: Salary Range | B1: # of Jobs
A2: $0–$25K | B2: =COUNTIFS(jobs[salary_year_avg], ">= 0", jobs[salary_year_avg], "< 25000") -> 5
A3: $25K–$50K | B3: =COUNTIFS(jobs[salary_year_avg], ">= 25000", jobs[salary_year_avg], "< 50000") -> 340
A4: $50K–$75K | B4: =COUNTIFS(jobs[salary_year_avg], ">= 50000", jobs[salary_year_avg], "< 75000") -> 2404
A5: $75K–$100K | B5: =COUNTIFS(jobs[salary_year_avg], ">= 75000", jobs[salary_year_avg], "< 100000") -> 4873
A6: $100K–$125K | B6: =COUNTIFS(jobs[salary_year_avg], ">= 100000", jobs[salary_year_avg], "< 125000") -> 4571
A7: $125K–$150K | B7: =COUNTIFS(jobs[salary_year_avg], ">= 125000", jobs[salary_year_avg], "< 150000") -> 4060
A8: $150K–$175K | B8: =COUNTIFS(jobs[salary_year_avg], ">= 150000", jobs[salary_year_avg], "< 175000") -> 3130
A9: $175K–$200K | B9: =COUNTIFS(jobs[salary_year_avg], ">= 175000", jobs[salary_year_avg], "< 200000") -> 1254
A10: $200K–$225K | B10: =COUNTIFS(jobs[salary_year_avg], ">= 200000", jobs[salary_year_avg], "< 225000") -> 736
A11: $225K–$250K | B11: =COUNTIFS(jobs[salary_year_avg], ">= 225000", jobs[salary_year_avg], "< 250000") -> 290
A12: $250K+ | B12: =COUNTIF(jobs[salary_year_avg], ">= 250000") -> 339
B13: =SUM(B2:B12) -> 22002
A15: Data Analyst | B15: Data Scientist | C15: Data Engineer
A16: {=_xlfn._xlws.FILTER(jobs[salary_year_avg], jobs[﻿job_title_short] = A15)} -> 89000 | B16: {=_xlfn._xlws.FILTER(jobs[salary_year_avg], jobs[﻿job_title_short] = B15)} -> 109500 | C16: {=_xlfn._xlws.FILTER(jobs[salary_year_avg], jobs[﻿job_title_short] = C15)} -> 140000
A17: 90250 | B17: 228222 | C17: 120000
A18: 133285 | B18: 114000 | C18: 129500
A19: 62623 | B19: 157500 | C19: 185000
A20: 71300 | B20: 103128 | C20: 195000
A21: 43200 | B21: 157500 | C21: 97500
A22: 111175 | B22: 157500 | C22: 89000
A23: 89111.75 | B23: 70700 | C23: 80000
A24: 111175 | B24: 56700 | C24: 110000
A25: 120000 | B25: 124400 | C25: 70000
A26: 101500 | B26: 105700 | C26: 100000
A27: 70000 | B27: 95000 | C27: 111228.16
A28: 35000 | B28: 206500 | C28: 171000
... A4515: 75000 | B4515: 161044 | C4515: 150000
A4516: 111175 | B4516: 136000
A4517: 82500 | B4517: 90000
A4518: 148500 | B4518: 350000
A4519: 100000 | B4519: 165000
A4520: 200000 | B4520: 115000
A4521: 90000 | B4521: 225000
A4522: 95000 | B4522: 115000
A4523: 117160 | B4523: 224500
A4524: 93070 | B4524: 131867
A4525: 79500 | B4525: 90670
A4526: 125000 | B4526: 350000
A4527: 90000 | B4527: 155000
... A5465: 105000 | B5465: 125000
B5466: 125000
B5467: 169500
B5468: 200000
B5469: 83850
B5470: 80000
B5471: 160000
B5472: 165000
B5473: 175000
B5474: 72500
B5475: 155500
B5476: 127500
B5477: 190000
... B5937: 157500
